{
    "key": "group_57ab528b9168e",
    "title": "Other Pages",
    "fields": [
        {
            "key": "field_57ab529ce8d7c",
            "label": "Imprint page link",
            "name": "imprint_page_link",
            "type": "page_link",
            "instructions": "This link will be displayed in the footer.",
            "required": 0,
            "conditional_logic": 0,
            "wrapper": {
                "width": "",
                "class": "",
                "id": ""
            },
            "post_type": [
                "page"
            ],
            "taxonomy": [],
            "allow_null": 0,
            "multiple": 0,
            "allow_archives": 1
        },
        {
            "key": "field_595ca6a1ef56a",
            "label": "Facebook Page URL",
            "name": "facebook_page_url",
            "type": "url",
            "instructions": "Change the URL for the Facebook icon in the footer here",
            "required": 0,
            "conditional_logic": 0,
            "wrapper": {
                "width": "",
                "class": "",
                "id": ""
            },
            "default_value": "",
            "placeholder": ""
        },
        {
            "key": "field_595ca6ef143aa",
            "label": "Twitter URL",
            "name": "twitter_url",
            "type": "url",
            "instructions": "Change the URL for the Twitter icon in the footer here",
            "required": 0,
            "conditional_logic": 0,
            "wrapper": {
                "width": "",
                "class": "",
                "id": ""
            },
            "default_value": "",
            "placeholder": ""
        },
        {
            "key": "field_590c58eba8d21",
            "label": "Stories Overview Page Introduction",
            "name": "story_archive_page_introduction",
            "type": "wysiwyg",
            "instructions": "",
            "required": 0,
            "conditional_logic": 0,
            "wrapper": {
                "width": "",
                "class": "",
                "id": ""
            },
            "default_value": "",
            "tabs": "all",
            "toolbar": "full",
            "media_upload": 1,
            "delay": 0
        },
        {
            "key": "field_591d4fb3449e2",
            "label": "Stories Overview Excluded Categories",
            "name": "story_archive_excluded_categories",
            "type": "taxonomy",
            "instructions": "",
            "required": 0,
            "conditional_logic": 0,
            "wrapper": {
                "width": "",
                "class": "",
                "id": ""
            },
            "taxonomy": "category",
            "field_type": "checkbox",
            "allow_null": 0,
            "add_term": 0,
            "save_terms": 0,
            "load_terms": 0,
            "return_format": "id",
            "multiple": 0
        },
        {
            "key": "field_590c5ac6d28a4",
            "label": "People Overview Page Introduction",
            "name": "participant_archive_page_introduction_copy",
            "type": "wysiwyg",
            "instructions": "",
            "required": 0,
            "conditional_logic": 0,
            "wrapper": {
                "width": "",
                "class": "",
                "id": ""
            },
            "default_value": "",
            "tabs": "all",
            "toolbar": "full",
            "media_upload": 1,
            "delay": 0
        },
        {
            "key": "field_591d5e45350b8",
            "label": "Lab Story Categories",
            "name": "lab_story_categories",
            "type": "taxonomy",
            "instructions": "",
            "required": 0,
            "conditional_logic": 0,
            "wrapper": {
                "width": "",
                "class": "",
                "id": ""
            },
            "taxonomy": "category",
            "field_type": "checkbox",
            "allow_null": 0,
            "add_term": 0,
            "save_terms": 0,
            "load_terms": 0,
            "return_format": "id",
            "multiple": 0
        },
        {
            "key": "field_591d814f3ed3e",
            "label": "Lab Explanation Page",
            "name": "lab_explanation_page",
            "type": "post_object",
            "instructions": "This is the page to which the 'find out more about ..' Lab sub-pages refers to.",
            "required": 0,
            "conditional_logic": 0,
            "wrapper": {
                "width": "",
                "class": "",
                "id": ""
            },
            "post_type": [
                "page",
                "story"
            ],
            "taxonomy": [],
            "allow_null": 0,
            "multiple": 0,
            "return_format": "object",
            "ui": 1
        },
        {
            "key": "field_591d81c3a8bb4",
            "label": "Lab Explanation Text",
            "name": "lab_explanation_Text",
            "type": "text",
            "instructions": "It is required to add a %s here, because it will be replaced by the word \/ link to the page.",
            "required": 0,
            "conditional_logic": 0,
            "wrapper": {
                "width": "",
                "class": "",
                "id": ""
            },
            "default_value": "Read more about %s",
            "placeholder": "",
            "prepend": "",
            "append": "",
            "maxlength": ""
        },
        {
            "key": "field_591d81f6a8bb5",
            "label": "Lab Explanation Link Text",
            "name": "lab_explanation_link_text",
            "type": "text",
            "instructions": "This is the word which will be used as the link's text.",
            "required": 0,
            "conditional_logic": 0,
            "wrapper": {
                "width": "",
                "class": "",
                "id": ""
            },
            "default_value": "prototypes",
            "placeholder": "",
            "prepend": "",
            "append": "",
            "maxlength": ""
        },
        {
            "key": "field_5947eb390d40f",
            "label": "Story Update Form Page",
            "name": "story_update_form_page",
            "type": "post_object",
            "instructions": "",
            "required": 0,
            "conditional_logic": 0,
            "wrapper": {
                "width": "",
                "class": "",
                "id": ""
            },
            "post_type": [
                "page"
            ],
            "taxonomy": [],
            "allow_null": 0,
            "multiple": 0,
            "return_format": "object",
            "ui": 1
        }
    ],
    "location": [
        [
            {
                "param": "options_page",
                "operator": "==",
                "value": "acf-options-pages"
            }
        ]
    ],
    "menu_order": 0,
    "position": "normal",
    "style": "default",
    "label_placement": "top",
    "instruction_placement": "label",
    "hide_on_screen": "",
    "active": 1,
    "description": "",
    "modified": 1499244294
}